<?xml version="1.0" encoding="utf-8"?>
<LanguageData>
  <!--<Moyo_Tail.label>хвост</Moyo_Tail.label>-->
  <!--<MoyoHeart.label>Сердце</MoyoHeart.label>-->
  <!--<HexapodHead.label>голова</HexapodHead.label>-->
  <!--<HexapodHeadShell.label>голова</HexapodHeadShell.label>-->
  <!--<Hexapod_TentacleJoint.label>Соединение щупалец</Hexapod_TentacleJoint.label>-->
  <!--<Hexapod_Tentacle.label>щупальце</Hexapod_Tentacle.label>-->
  <!--<pressurepod_ArmJoint.label>Подключение руки</pressurepod_ArmJoint.label>-->
  <!--<pressurepod_club.label>дробилка</pressurepod_club.label>-->
  <!--<pressurepod_Leg.label>Нога</pressurepod_Leg.label>-->
  <!--<PressurePod_Seg1.labelShort>Узел щупа давления</PressurePod_Seg1.labelShort>-->
  <!--<PressurePod_Seg1.label>Первое слово</PressurePod_Seg1.label>-->
  <!--<PressurePod_Seg2.labelShort>Узел щупа давления</PressurePod_Seg2.labelShort>-->
  <!--<PressurePod_Seg2.label>Второе слово</PressurePod_Seg2.label>-->
  <!--<PressurePod_Seg3.labelShort>Узел щупа давления</PressurePod_Seg3.labelShort>-->
  <!--<PressurePod_Seg3.label>Третее слово</PressurePod_Seg3.label>-->
  <!--<PressurePod_Seg4.labelShort>Узел щупа давления</PressurePod_Seg4.labelShort>-->
  <!--<PressurePod_Seg4.label>Четвёртое слово</PressurePod_Seg4.label>-->
  <!--<PressurePod_Seg5.labelShort>Узел щупа давления</PressurePod_Seg5.labelShort>-->
  <!--<PressurePod_Seg5.label>Пятое слово</PressurePod_Seg5.label>-->

</LanguageData>